tool/__init__.py
tool/utils.py
zq_pt_albert-0.1.2.dist-info/METADATA
zq_pt_albert-0.1.2.dist-info/WHEEL
zq_pt_albert-0.1.2.dist-info/top_level.txt
zq_pt_albert-0.1.2.dist-info/RECORD
