Metadata-Version: 2.1
Name: zq-pt-albert
Version: 0.1.2
Summary: google small zh albert tf
Author: zhangqi
Author-email: zhangqi23@163.com
Requires-Dist: xlrd (==1.2.0)
Requires-Dist: xlwt
Requires-Dist: xlutils
Requires-Dist: configparser
Requires-Dist: xlsxwriter (==3.0.1)
Requires-Dist: tqdm
